{
  "id": "5e7fa9e991ab7cec5eafde11d51aee9f7860a5c3a08bbdb379cc8a4873063c61",
  "title": "M04X04X0.7_Din913_Ep06 1",
  "path_original": "C:\\Users\\anton\\Desktop\\MBiblliotecaMec\\entrada\\Merdas Mecanica\\Nuno-Engenharia Mecânica\\3ºAno\\3ºAno\\1ºSemestre\\Anteriores\\Projeto Moldes\\M1641004\\Carburador\\M04x04x0.7_DIN913_EP06-1.sldprt",
  "disciplina": "projeto-de-moldes",
  "tipo": "trabalhos-projetos",
  "ano": 3,
  "semestre": 1,
  "storage_release_tag": null,
  "storage_url": null,
  "confianca_media": 0.0,
  "assembled_at": "2026-07-03T21:04:19.909390"
}