{
  "id": "123779dc8cca8b2d4441cabe03954212c76c5a7a9c44794824e04c55ef45b0be",
  "title": "Nztpic000000_Nl(Nztpic160850)",
  "path_original": "C:\\Users\\anton\\Desktop\\MBiblliotecaMec\\entrada\\Merdas Mecanica\\Nuno-Engenharia Mecânica\\3ºAno\\3ºAno\\1ºSemestre\\Anteriores\\Projeto Moldes\\M1641004\\Carburador\\NZTPIC000000_NL(NZTPIC160850).sldprt",
  "disciplina": "projeto-de-moldes",
  "tipo": "trabalhos-projetos",
  "ano": 3,
  "semestre": 1,
  "storage_release_tag": null,
  "storage_url": null,
  "confianca_media": 0.0,
  "assembled_at": "2026-07-03T21:04:19.940218"
}