{
  "id": "42cdc0b758a4e45496766e5f1298874e49dd679cc7eaef8694d8ab6e7cd3f805",
  "title": "Z20_30X140",
  "path_original": "C:\\Users\\anton\\Desktop\\MBiblliotecaMec\\entrada\\Merdas Mecanica\\Nuno-Engenharia Mecânica\\3ºAno\\3ºAno\\1ºSemestre\\Anteriores\\Projeto Moldes\\M1641004\\Guiamento\\Z20_30x140.SLDPRT",
  "disciplina": "projeto-de-moldes",
  "tipo": "trabalhos-projetos",
  "ano": 3,
  "semestre": 1,
  "storage_release_tag": null,
  "storage_url": null,
  "confianca_media": 0.0,
  "assembled_at": "2026-07-03T21:04:20.164953"
}