{
  "id": "916f82e57ea1a3a7337fa52001c5102f0675a1408dac08f76fcd3659c6f2c1b4",
  "title": "Z55_18X3_1",
  "path_original": "C:\\Users\\anton\\Desktop\\MBiblliotecaMec\\entrada\\Merdas Mecanica\\Gonçalo- Engenharia Mecânica\\3ºAno\\1ºSemestre\\Projeto de Moldes\\Acessorios\\Parafusos\\Z55_18x3_1.SLDPRT",
  "disciplina": "projeto-de-moldes",
  "tipo": "trabalhos-projetos",
  "ano": 3,
  "semestre": 1,
  "storage_release_tag": null,
  "storage_url": null,
  "confianca_media": 0.0,
  "assembled_at": "2026-07-03T21:04:02.537187"
}