{
  "id": "291dd4e6f84583999aa59a1b5f3e4d7c66f1aa94404295525fc646ba0f1cd982",
  "title": "Cap11 Elementos_De_Maquinas_Lig_Pecas_Roscadas",
  "path_original": "C:\\Users\\anton\\Desktop\\MBiblliotecaMec\\entrada\\Merdas Mecanica\\Joel\\Engenharia Mecanica 2º ano\\2º Semestre\\DCM\\Aulas-Acetatos\\Cap11-Elementos_de_Maquinas_LIG_PECAS_ROSCADAS.pdf",
  "disciplina": "desenho-de-construcao-mecanica",
  "tipo": "teoria",
  "ano": 2,
  "semestre": 2,
  "storage_release_tag": null,
  "storage_url": null,
  "confianca_media": 0.0,
  "assembled_at": "2026-07-03T21:04:12.832729"
}