{
  "id": "00980ba55414e34cf22a6be26714c674d59a0345c182f3109abac04639673f0a",
  "title": "Radiator",
  "path_original": "C:\\Users\\anton\\Desktop\\MBiblliotecaMec\\entrada\\Merdas Mecanica\\3ºAno\\1ºSemestre\\Projeto Mecânico\\Projeto\\Montagem_Final_Camião_Grua\\Workspaces\\Workspace\\CHASSIS 2\\Radiator.iam",
  "disciplina": "projeto-mecanico",
  "tipo": "trabalhos-projetos",
  "ano": 3,
  "semestre": 1,
  "storage_release_tag": null,
  "storage_url": null,
  "confianca_media": 0.0,
  "assembled_at": "2026-07-03T21:03:54.124185"
}