{
  "id": "f1248c0186166b7085c869914c4dc81921ac690335257802c15ca372d7956b3c",
  "title": "1 Calor EspecíFico SóLidos E LíQuidos IncompressíVeis",
  "path_original": "C:\\Users\\anton\\Desktop\\MBiblliotecaMec\\entrada\\Merdas Mecanica\\2ºAno\\1ºSemestre\\Termodinâmica\\PE1\\Apontamentos\\Aula 6\\1 Calor específico sólidos e líquidos incompressíveis.pdf",
  "disciplina": "termodinamica",
  "tipo": "resumos",
  "ano": 2,
  "semestre": 1,
  "storage_release_tag": null,
  "storage_url": null,
  "confianca_media": 0.0,
  "assembled_at": "2026-07-03T21:03:46.537246"
}