{
  "id": "7bf32bcfc21fca217684578f6b987abab64651eaf065e47419c1bfa0f22754fd",
  "title": "2.Screw Handle",
  "path_original": "C:\\Users\\anton\\Desktop\\MBiblliotecaMec\\entrada\\Merdas Mecanica\\Gonçalo- Engenharia Mecânica\\2ºAno\\1º Semestre\\MAC\\trab solid edge\\Trabalho 2\\2.Screw Handle.par",
  "disciplina": "modelacao-assistida-por-computador",
  "tipo": "trabalhos-projetos",
  "ano": 2,
  "semestre": 1,
  "storage_release_tag": null,
  "storage_url": null,
  "confianca_media": 0.0,
  "assembled_at": "2026-07-03T21:04:00.948836"
}