{
  "id": "c409fcc0bd5c196a024588f8e69e08d7e6321f0509e3b427e797c7302da59d76",
  "title": "4211713",
  "path_original": "C:\\Users\\anton\\Desktop\\MBiblliotecaMec\\entrada\\Merdas Mecanica\\Nuno-Engenharia Mecânica\\2ºAno\\1ºSemestre\\MAC\\Trabalho Final\\Peças_2\\4211713.par",
  "disciplina": "modelacao-assistida-por-computador",
  "tipo": "trabalhos-projetos",
  "ano": 2,
  "semestre": 1,
  "storage_release_tag": null,
  "storage_url": null,
  "confianca_media": 0.0,
  "assembled_at": "2026-07-03T21:04:16.899306"
}