{
  "id": "0b21899d640f946e12e8b0aaecfbcf5430c73921332af04312b1a3fe2b01b0e2",
  "title": "Ejer3",
  "path_original": "C:\\Users\\anton\\Desktop\\MBiblliotecaMec\\entrada\\Merdas Mecanica\\Nuno-Engenharia Mecânica\\3ºAno\\3ºAno\\1ºSemestre\\Automação Industrial\\Trabalho\\Pneumática\\FluidSim - anos anteriores\\ejer3.ct",
  "disciplina": "automacao-industrial",
  "tipo": "trabalhos-projetos",
  "ano": 3,
  "semestre": 1,
  "storage_release_tag": null,
  "storage_url": null,
  "confianca_media": 0.0,
  "assembled_at": "2026-07-03T21:04:20.856863"
}