{
  "id": "a1032372a44c6e2cab681a6d5679f948a009f6bac4bc49704be4ba2ed1708c47",
  "title": "Exercício 4 Static 1",
  "path_original": "C:\\Users\\anton\\Desktop\\MBiblliotecaMec\\entrada\\Merdas Mecanica\\2ºAno\\2ºSemestre\\Engenharia Assistida por Computador\\EAC - Exercícios PL\\Exercício 4\\Exercício 4-Static 1.CWR",
  "disciplina": "engenharia-assistida-por-computador",
  "tipo": "fichas-exercicios",
  "ano": 2,
  "semestre": 2,
  "storage_release_tag": null,
  "storage_url": null,
  "confianca_media": 0.0,
  "assembled_at": "2026-07-03T21:03:47.003134"
}