{
  "id": "31fd9cc6701471da8a6aa592a5dbf6c868509c1dc07ac8882af20b7f751c684c",
  "title": "Omi_Instabilidade_Elastica_2024_Resumido",
  "path_original": "C:\\Users\\anton\\Desktop\\MBiblliotecaMec\\entrada\\Merdas Mecanica\\2ºAno\\2ºSemestre\\Orgãos de Máquinas I\\Estudo\\OM I PE1 - Fichas e Slides\\Slides\\OMI_instabilidade_elastica_2024_RESUMIDO.pdf",
  "disciplina": "orgaos-de-maquinas-i",
  "tipo": "teoria",
  "ano": 2,
  "semestre": 2,
  "storage_release_tag": null,
  "storage_url": null,
  "confianca_media": 0.0,
  "assembled_at": "2026-07-03T21:03:47.672719"
}