{
  "id": "9665b59f77261ef98bd3181eabc0bcf825a1f92eb50b0472ad6a6eea2e49386b",
  "title": "Apcer Guia Iso 90012015",
  "path_original": "C:\\Users\\anton\\Desktop\\MBiblliotecaMec\\entrada\\Merdas Mecanica\\3ºAno\\2ºSemestre\\Qualidade e Gestão de Recursos\\Norma\\APCER GUIA ISO 90012015.pdf",
  "disciplina": "qualidade-e-gestao-de-recursos",
  "tipo": "testes-exames",
  "ano": 3,
  "semestre": 2,
  "storage_release_tag": null,
  "storage_url": null,
  "confianca_media": 0.0,
  "assembled_at": "2026-07-03T21:03:55.307052"
}