{
  "id": "eb576817431c9393ae8533af64cdaf40bd338f59d109416d18d7e2d5d1af5668",
  "title": "Tp2   Enunciado   Ferramentas Básicas",
  "path_original": "C:\\Users\\anton\\Desktop\\MBiblliotecaMec\\entrada\\Merdas Mecanica\\3ºAno\\2ºSemestre\\Qualidade e Gestão de Recursos\\Trabalho Escrito 2\\TP2 - Enunciado - Ferramentas básicas.pdf",
  "disciplina": "qualidade-e-gestao-de-recursos",
  "tipo": "testes-exames",
  "ano": 3,
  "semestre": 2,
  "storage_release_tag": null,
  "storage_url": null,
  "confianca_media": 0.0,
  "assembled_at": "2026-07-03T21:03:55.494508"
}