{
  "id": "6939316bd98dfcc5fef9ee899e6926428046db735a822473cc81531603875d12",
  "title": "Frame Part 1",
  "path_original": "C:\\Users\\anton\\Desktop\\MBiblliotecaMec\\entrada\\Merdas Mecanica\\Nuno-Engenharia Mecânica\\3ºAno\\3ºAno\\1ºSemestre\\PAF\\Trabalhos\\Pratico\\Trabalho paf\\Peças\\Tapete 2\\Tapete 2\\Frame part 1.SLDPRT",
  "disciplina": "processos-avancados-de-fabrico",
  "tipo": "trabalhos-projetos",
  "ano": 3,
  "semestre": 1,
  "storage_release_tag": null,
  "storage_url": null,
  "confianca_media": 0.0,
  "assembled_at": "2026-07-03T21:04:21.886417"
}