{
  "id": "2273c8dc1c90f5078bb27e4c6ea40eab59070b7a9b8e049dd1fd06f7fc409efe",
  "title": "Guião_Pitchs",
  "path_original": "C:\\Users\\anton\\Desktop\\MBiblliotecaMec\\entrada\\Merdas Mecanica\\Joel\\Engenharia Mecanica 3º ano\\2º Semestre\\Inovação e Empreendedorismo\\Guião do Trabalho\\Guião_Pitchs.pdf",
  "disciplina": "inovacao-e-empreendedorismo",
  "tipo": "trabalhos-projetos",
  "ano": 3,
  "semestre": 2,
  "storage_release_tag": null,
  "storage_url": null,
  "confianca_media": 0.0,
  "assembled_at": "2026-07-03T21:04:14.634328"
}