{
  "id": "66c59ea4455ec1f5242a8ec9a9d85918dcc49b5d91c4798eb8e0337c669472a8",
  "title": "B2Bec844 93Ca 4D89 Ad29 419Cdd0Bf4A3",
  "path_original": "C:\\Users\\anton\\Desktop\\MBiblliotecaMec\\entrada\\Merdas Mecanica\\2ºAno\\1ºSemestre\\Processos de Transformação de Plásticos\\TL2\\Imagens_TL2\\B2BEC844-93CA-4D89-AD29-419CDD0BF4A3.jpg",
  "disciplina": "processos-transformacao-plasticos",
  "tipo": "teoria",
  "ano": 2,
  "semestre": 1,
  "storage_release_tag": null,
  "storage_url": null,
  "confianca_media": 0.0,
  "assembled_at": "2026-07-03T21:03:45.958664"
}