{
  "id": "880adbbf3ce4b845c312e83059e76b47779e7d952dac754c7f323e6bbf55861c",
  "title": "Ár Vacuo",
  "path_original": "C:\\Users\\anton\\Desktop\\MBiblliotecaMec\\entrada\\Merdas Mecanica\\2ºAno\\1ºSemestre\\Processos de Transformação de Plásticos\\TL2\\Imagens_TL2\\ÁR VACUO.jpg",
  "disciplina": "processos-transformacao-plasticos",
  "tipo": "teoria",
  "ano": 2,
  "semestre": 1,
  "storage_release_tag": null,
  "storage_url": null,
  "confianca_media": 0.0,
  "assembled_at": "2026-07-03T21:03:46.101403"
}