{
  "id": "a9135e959ba915acc0d97472df63b506a89f44331c0e0f6139d82205cebc053e",
  "title": "Barra_De_Calibragem_2_3",
  "path_original": "C:\\Users\\anton\\Desktop\\MBiblliotecaMec\\entrada\\Merdas Mecanica\\Gonçalo- Engenharia Mecânica\\3ºAno\\2ºSemestre\\Estagio Curricular\\Estágio somema\\M5203\\Barra_de_Calibragem_2_3.CATPart",
  "disciplina": "estagio",
  "tipo": "teoria",
  "ano": 3,
  "semestre": 2,
  "storage_release_tag": null,
  "storage_url": null,
  "confianca_media": 0.0,
  "assembled_at": "2026-07-03T21:04:05.084485"
}