{
  "id": "9254a1dcbc93aa5a8c97da7ae3c96080706b7dbbbd00f7629e135688643af06a",
  "title": "Cooling Circuits   Core",
  "path_original": "C:\\Users\\anton\\Desktop\\MBiblliotecaMec\\entrada\\Merdas Mecanica\\Gonçalo- Engenharia Mecânica\\3ºAno\\2ºSemestre\\Estagio Curricular\\Estágio somema\\Nova pasta\\M5203_MOLD_3D_Rev0_11-09-2020\\Cooling circuits - Core.CATPart",
  "disciplina": "estagio",
  "tipo": "teoria",
  "ano": 3,
  "semestre": 2,
  "storage_release_tag": null,
  "storage_url": null,
  "confianca_media": 0.0,
  "assembled_at": "2026-07-03T21:04:06.117938"
}