{
  "id": "7ef4aac318158be95095ed7caa66ee883d5238baa07a43af556d5c09a688b25c",
  "title": "Teste01_004",
  "path_original": "C:\\Users\\anton\\Desktop\\MBiblliotecaMec\\entrada\\Merdas Mecanica\\Nuno-Engenharia Mecânica\\3ºAno\\3ºAno\\1ºSemestre\\Simulação Computacional\\TrabalhoFinal\\Finalfinal\\Analysis\\Run01\\Teste01_004.f2c",
  "disciplina": "desconhecido",
  "tipo": "trabalhos-projetos",
  "ano": 3,
  "semestre": 1,
  "storage_release_tag": null,
  "storage_url": null,
  "confianca_media": 0.0,
  "assembled_at": "2026-07-03T21:04:23.289616"
}