{
  "id": "5df6c9889cab22d085f59280ee7a087d8f0653233e42a7cbfb14b826d9ed51a5",
  "title": "Lattice_Grande (4)",
  "path_original": "C:\\Users\\anton\\Desktop\\MBiblliotecaMec\\entrada\\Merdas Mecanica\\Francisca- Engenharia Mecânica\\3º Ano\\PAF\\ent2 - projeto caixa\\fotos\\teste estruturas 2\\lattice_grande (4).jpg",
  "disciplina": "processos-avancados-de-fabrico",
  "tipo": "testes-exames",
  "ano": 3,
  "semestre": 1,
  "storage_release_tag": null,
  "storage_url": null,
  "confianca_media": 0.0,
  "assembled_at": "2026-07-03T21:03:59.950602"
}