{
  "id": "4a3d610da23f13c276b5c4e263aeb1df0131334de73fa9e6074010ab2be941b1",
  "title": "Ejer 1",
  "path_original": "C:\\Users\\anton\\Desktop\\MBiblliotecaMec\\entrada\\Merdas Mecanica\\Nuno-Engenharia Mecânica\\3ºAno\\3ºAno\\1ºSemestre\\Automação Industrial\\Trabalho\\Pneumática\\FluidSim - anos anteriores\\Ejer-1.ct",
  "disciplina": "automacao-industrial",
  "tipo": "trabalhos-projetos",
  "ano": 3,
  "semestre": 1,
  "storage_release_tag": null,
  "storage_url": null,
  "confianca_media": 0.0,
  "assembled_at": "2026-07-03T21:04:20.850825"
}