{
  "id": "b0aeb2de0ac71237023368aa79075d1e6ff685818e7be18df38470e76a7537da",
  "title": "Anéis De Centragem",
  "path_original": "C:\\Users\\anton\\Desktop\\MBiblliotecaMec\\entrada\\Merdas Mecanica\\Gonçalo- Engenharia Mecânica\\3ºAno\\2ºSemestre\\Estagio verao\\Plasitech\\Anéis de centragem.dwg",
  "disciplina": "estagio",
  "tipo": "teoria",
  "ano": 3,
  "semestre": 2,
  "storage_release_tag": null,
  "storage_url": null,
  "confianca_media": 0.0,
  "assembled_at": "2026-07-03T21:04:11.507667"
}