{
  "id": "678bbb6c6093bcde4f5b6aff1ff8eed8e7861f5425a9eef5bdb8b184879c7b67",
  "title": "M5203 Surfaces_Duplicated_54",
  "path_original": "C:\\Users\\anton\\Desktop\\MBiblliotecaMec\\entrada\\Merdas Mecanica\\Gonçalo- Engenharia Mecânica\\3ºAno\\2ºSemestre\\Estagio Curricular\\Estágio somema\\Nova pasta\\M5203_MOLD_3D_Rev0_11-09-2020\\M5203-SURFACES_Duplicated_54.CATPart",
  "disciplina": "estagio",
  "tipo": "teoria",
  "ano": 3,
  "semestre": 2,
  "storage_release_tag": null,
  "storage_url": null,
  "confianca_media": 0.0,
  "assembled_at": "2026-07-03T21:04:08.221694"
}