{
  "id": "bace7138d0243a97b7a78f0225815430dc79bf5769b11377cc83d36b49a3c11f",
  "title": "M5203 Surfaces_Duplicated_688",
  "path_original": "C:\\Users\\anton\\Desktop\\MBiblliotecaMec\\entrada\\Merdas Mecanica\\Gonçalo- Engenharia Mecânica\\3ºAno\\2ºSemestre\\Estagio Curricular\\Estágio somema\\Nova pasta\\M5203_MOLD_3D_Rev0_11-09-2020\\M5203-SURFACES_Duplicated_688.CATPart",
  "disciplina": "estagio",
  "tipo": "teoria",
  "ano": 3,
  "semestre": 2,
  "storage_release_tag": null,
  "storage_url": null,
  "confianca_media": 0.0,
  "assembled_at": "2026-07-03T21:04:08.689280"
}