{
  "id": "9dedfc688c068ebc0ca0c5a3c44619f36e0696d715a3d9ece9c04d5849fd7abf",
  "title": "M5203 Surfaces_Duplicated_1078",
  "path_original": "C:\\Users\\anton\\Desktop\\MBiblliotecaMec\\entrada\\Merdas Mecanica\\Gonçalo- Engenharia Mecânica\\3ºAno\\2ºSemestre\\Estagio Curricular\\Estágio somema\\Nova pasta\\M5203_MOLD_3D_Rev0_11-09-2020\\M5203-SURFACES_Duplicated_1078.CATPart",
  "disciplina": "estagio",
  "tipo": "teoria",
  "ano": 3,
  "semestre": 2,
  "storage_release_tag": null,
  "storage_url": null,
  "confianca_media": 0.0,
  "assembled_at": "2026-07-03T21:04:06.553460"
}