{
  "id": "d369178ad203d4202d258ed5544cc7a565edb03c04ad9451f8e3303316a98312",
  "title": "P451__5",
  "path_original": "C:\\Users\\anton\\Desktop\\MBiblliotecaMec\\entrada\\Merdas Mecanica\\Gonçalo- Engenharia Mecânica\\3ºAno\\2ºSemestre\\Estagio Curricular\\Estágio somema\\M5203\\P451__5.CATPart",
  "disciplina": "estagio",
  "tipo": "teoria",
  "ano": 3,
  "semestre": 2,
  "storage_release_tag": null,
  "storage_url": null,
  "confianca_media": 0.0,
  "assembled_at": "2026-07-03T21:04:05.276595"
}