{
  "id": "93e69b03b8cb46beeed085d1ebe1348e5f7fe4e991ce0a0087723723c3dd6409",
  "title": "Ref_Stop_Pins",
  "path_original": "C:\\Users\\anton\\Desktop\\MBiblliotecaMec\\entrada\\Merdas Mecanica\\Gonçalo- Engenharia Mecânica\\3ºAno\\2ºSemestre\\Estagio Curricular\\Estágio somema\\Nova pasta\\M5203_MOLD_3D_Rev0_11-09-2020\\Ref_Stop_Pins.CATPart",
  "disciplina": "estagio",
  "tipo": "teoria",
  "ano": 3,
  "semestre": 2,
  "storage_release_tag": null,
  "storage_url": null,
  "confianca_media": 0.0,
  "assembled_at": "2026-07-03T21:04:10.651527"
}