{
  "id": "f618aee614a37f0e46c70d0ea9d1c0f8f5906cb4eb8b0e20d4f8f91008159f10",
  "title": "Laser Core",
  "path_original": "C:\\Users\\anton\\Desktop\\MBiblliotecaMec\\entrada\\Merdas Mecanica\\Nuno-Engenharia Mecânica\\3ºAno\\3ºAno\\1ºSemestre\\PAF\\Trabalhos\\Pratico\\Trabalho paf\\Peças\\Cabeça laser\\Cabeça 1\\Laser core.igs",
  "disciplina": "processos-avancados-de-fabrico",
  "tipo": "trabalhos-projetos",
  "ano": 3,
  "semestre": 1,
  "storage_release_tag": null,
  "storage_url": null,
  "confianca_media": 0.0,
  "assembled_at": "2026-07-03T21:04:21.128385"
}