{
  "id": "cb94ef1b81bc8ff46a1a0fd0864738bad18c70ad73f0c6b3a860351c1c63218d",
  "title": "Sr4",
  "path_original": "C:\\Users\\anton\\Desktop\\MBiblliotecaMec\\entrada\\Merdas Mecanica\\Nuno-Engenharia Mecânica\\3ºAno\\3ºAno\\1ºSemestre\\PAF\\Trabalhos\\Pratico\\Trabalho paf\\Peças\\Leitor QR code\\SR4.PNG",
  "disciplina": "processos-avancados-de-fabrico",
  "tipo": "trabalhos-projetos",
  "ano": 3,
  "semestre": 1,
  "storage_release_tag": null,
  "storage_url": null,
  "confianca_media": 0.0,
  "assembled_at": "2026-07-03T21:04:21.210842"
}