{
  "id": "2498a24551a5787da605f77bcd13b425ca1474afe8f2bd7f6f2e25eebbdf866d",
  "title": "Trabalho",
  "path_original": "C:\\Users\\anton\\Desktop\\MBiblliotecaMec\\entrada\\Merdas Mecanica\\Nuno-Engenharia Mecânica\\3ºAno\\3ºAno\\1ºSemestre\\PAF\\Trabalhos\\Teorica\\Trabalho.doc",
  "disciplina": "processos-avancados-de-fabrico",
  "tipo": "trabalhos-projetos",
  "ano": 3,
  "semestre": 1,
  "storage_release_tag": null,
  "storage_url": null,
  "confianca_media": 0.0,
  "assembled_at": "2026-07-03T21:04:21.978027"
}