{
  "id": "afb2b89164c61b7ab9bfe3ca1ee386a4dbb963c7162a33afad6f64bf92fbbb45",
  "title": "Din5464",
  "path_original": "C:\\Users\\anton\\Desktop\\MBiblliotecaMec\\entrada\\Merdas Mecanica\\3ºAno\\1ºSemestre\\Conceção e Desenvolvimento do Produto\\Trabalhos Teóricos\\T3\\Modelação_Produto\\Design Data\\Design Accelerator\\Tables\\Splines\\DIN5464.xml",
  "disciplina": "concecao-e-desenvolvimento-de-produto",
  "tipo": "teoria",
  "ano": 3,
  "semestre": 1,
  "storage_release_tag": null,
  "storage_url": null,
  "confianca_media": 0.0,
  "assembled_at": "2026-07-03T21:03:50.268996"
}