{
  "id": "40f187e4b3fdeab4814e4ae761954ff3336340432b6b6587a28003c330687fa0",
  "title": "Grades_It_Metric",
  "path_original": "C:\\Users\\anton\\Desktop\\MBiblliotecaMec\\entrada\\Merdas Mecanica\\3ºAno\\1ºSemestre\\Conceção e Desenvolvimento do Produto\\Trabalhos Teóricos\\T3\\Modelação_Produto\\Design Data\\Design Accelerator\\Tables\\LimFit\\Grades_IT_Metric.xml",
  "disciplina": "concecao-e-desenvolvimento-de-produto",
  "tipo": "teoria",
  "ano": 3,
  "semestre": 1,
  "storage_release_tag": null,
  "storage_url": null,
  "confianca_media": 0.0,
  "assembled_at": "2026-07-03T21:03:49.663924"
}