{
  "id": "7cd2dea67822c0f4eff0170d84f4f9e7842b0c1a5e113a9119e0c8f122009cb5",
  "title": "Jisb1801_B",
  "path_original": "C:\\Users\\anton\\Desktop\\MBiblliotecaMec\\entrada\\Merdas Mecanica\\3ºAno\\1ºSemestre\\Conceção e Desenvolvimento do Produto\\Trabalhos Teóricos\\T3\\Modelação_Produto\\Design Data\\Design Accelerator\\Tables\\Chains\\RollerChains\\JISB1801_B.jpg",
  "disciplina": "concecao-e-desenvolvimento-de-produto",
  "tipo": "teoria",
  "ano": 3,
  "semestre": 1,
  "storage_release_tag": null,
  "storage_url": null,
  "confianca_media": 0.0,
  "assembled_at": "2026-07-03T21:03:49.336719"
}