{
  "id": "7164d38d96d63e4d76c79e7a7022f0863c462a7d30eb02f4f1c17d0cba727fb7",
  "title": "Pdata_Conv",
  "path_original": "C:\\Users\\anton\\Desktop\\MBiblliotecaMec\\entrada\\Merdas Mecanica\\Gonçalo- Engenharia Mecânica\\3ºAno\\1ºSemestre\\Automação\\Modulo 2\\pratica\\Programa\\IM\\HMI\\S\\1\\Generates\\pdata_conv.srt",
  "disciplina": "automacao-industrial",
  "tipo": "fichas-exercicios",
  "ano": 3,
  "semestre": 1,
  "storage_release_tag": null,
  "storage_url": null,
  "confianca_media": 0.0,
  "assembled_at": "2026-07-03T21:04:02.023197"
}