{
  "id": "df86e6909bc8be596fb6efdffd73eac6a986f251e7d731e3ff9f34460e43e05b",
  "title": "K1000_160X15_2.Stp",
  "path_original": "C:\\Users\\anton\\Desktop\\MBiblliotecaMec\\entrada\\Merdas Mecanica\\Gonçalo- Engenharia Mecânica\\3ºAno\\1ºSemestre\\Projeto de Moldes\\Acessorios\\Anel de centragem\\K1000_160x15_2.stp.SLDPRT",
  "disciplina": "projeto-de-moldes",
  "tipo": "trabalhos-projetos",
  "ano": 3,
  "semestre": 1,
  "storage_release_tag": null,
  "storage_url": null,
  "confianca_media": 0.0,
  "assembled_at": "2026-07-03T21:04:02.249168"
}