{
  "id": "08587f50214e936e6049d48b4f7ca36613e03ab3fbd2b5e3e750c2c339e3ba98",
  "title": "Mfctgk030000(Mfctgk030100)",
  "path_original": "C:\\Users\\anton\\Desktop\\MBiblliotecaMec\\entrada\\Merdas Mecanica\\Nuno-Engenharia Mecânica\\3ºAno\\3ºAno\\1ºSemestre\\Anteriores\\Projeto Moldes\\M1641004\\Carburador\\MFCTGK030000(MFCTGK030100).sldprt",
  "disciplina": "projeto-de-moldes",
  "tipo": "trabalhos-projetos",
  "ano": 3,
  "semestre": 1,
  "storage_release_tag": null,
  "storage_url": null,
  "confianca_media": 0.0,
  "assembled_at": "2026-07-03T21:04:19.914751"
}