{
  "id": "93646b0644433f1f9f9ba1fb5198a2cd7681ec2b5a664213f3dac658045bba8c",
  "title": "Processos Subtrativos",
  "path_original": "C:\\Users\\anton\\Desktop\\MBiblliotecaMec\\entrada\\Merdas Mecanica\\Nuno-Engenharia Mecânica\\3ºAno\\3ºAno\\2ºSemestre\\Seminário\\processos subtrativos.docx",
  "disciplina": "seminario",
  "tipo": "teoria",
  "ano": 3,
  "semestre": 2,
  "storage_release_tag": null,
  "storage_url": null,
  "confianca_media": 0.0,
  "assembled_at": "2026-07-03T21:04:24.375437"
}