{
  "id": "96c170e120902e0dfef0f4154bd0c6888884709bf287c2f1599669d187fa5321",
  "title": "Axle Hub Assy_1",
  "path_original": "C:\\Users\\anton\\Desktop\\MBiblliotecaMec\\entrada\\Merdas Mecanica\\3ºAno\\1ºSemestre\\Projeto Mecânico\\Projeto\\Montagem_Final_Camião_Grua\\Workspaces\\Workspace\\CHASSIS 2\\AXLE HUB ASSY_1.iam",
  "disciplina": "projeto-mecanico",
  "tipo": "trabalhos-projetos",
  "ano": 3,
  "semestre": 1,
  "storage_release_tag": null,
  "storage_url": null,
  "confianca_media": 0.0,
  "assembled_at": "2026-07-03T21:03:53.268642"
}