{
  "id": "17735cd7655da85ec574f60b9067e73a7c22907b3b5693481905885e4ba18048",
  "title": "Model1_2483",
  "path_original": "C:\\Users\\anton\\Desktop\\MBiblliotecaMec\\entrada\\Merdas Mecanica\\3ºAno\\1ºSemestre\\Projeto Mecânico\\Projeto\\Montagem_Final_Camião_Grua\\Workspaces\\Workspace\\CHASSIS 2\\model1_2483.ipt",
  "disciplina": "projeto-mecanico",
  "tipo": "trabalhos-projetos",
  "ano": 3,
  "semestre": 1,
  "storage_release_tag": null,
  "storage_url": null,
  "confianca_media": 0.0,
  "assembled_at": "2026-07-03T21:03:53.824626"
}