{
  "id": "6d922bf19dd057e87e021b64be6c30c5cc9acaed1fb4a0ccd68c33a920436bde",
  "title": "Montagem V2",
  "path_original": "C:\\Users\\anton\\Desktop\\MBiblliotecaMec\\entrada\\Merdas Mecanica\\3ºAno-gaspar\\3ºAno\\1ºSemestre\\Projeto Mecânico\\22_23\\imagens relatorio\\montagem v2.jpg",
  "disciplina": "projeto-mecanico",
  "tipo": "trabalhos-projetos",
  "ano": 3,
  "semestre": 1,
  "storage_release_tag": null,
  "storage_url": null,
  "confianca_media": 0.0,
  "assembled_at": "2026-07-03T21:03:56.418755"
}