{
  "id": "c03cec08ba6ed41a7ec9c6e60fde253a1861698515e8acef6046bb29752e38bc",
  "title": "Wd H 0645 3 00020_Part79",
  "path_original": "C:\\Users\\anton\\Desktop\\MBiblliotecaMec\\entrada\\Merdas Mecanica\\3ºAno\\1ºSemestre\\Projeto Mecânico\\Projeto\\Montagem_Final_Camião_Grua\\Workgroups\\NotInProject\\WD-H-0645-3-00020_PART79.ipt",
  "disciplina": "projeto-mecanico",
  "tipo": "trabalhos-projetos",
  "ano": 3,
  "semestre": 1,
  "storage_release_tag": null,
  "storage_url": null,
  "confianca_media": 0.0,
  "assembled_at": "2026-07-03T21:03:53.000255"
}