{
  "id": "6adaa01ab74f78e4a8fc9067a7b5b92ff9cad8676607d92c9d2cb5f5763e6446",
  "title": "10401876_1038252279534424_1825541016373677464_N",
  "path_original": "C:\\Users\\anton\\Desktop\\MBiblliotecaMec\\entrada\\Merdas Mecanica\\Nuno-Engenharia Mecânica\\2ºAno\\1ºSemestre\\PTP\\Anos anteriores\\PTP\\Anos_Anteriores\\PTP\\Aulas\\Fotos Aulas\\10401876_1038252279534424_1825541016373677464_n.jpg",
  "disciplina": "desconhecido",
  "tipo": "teoria",
  "ano": 2,
  "semestre": 1,
  "storage_release_tag": null,
  "storage_url": null,
  "confianca_media": 0.0,
  "assembled_at": "2026-07-03T21:04:17.481154"
}