{
  "id": "84c0e5f94507fef34f8a8fbc54de7dc51fb82043539cb58f72def25d95dd2386",
  "title": "Peça 9 Maquinaçao Roland",
  "path_original": "C:\\Users\\anton\\Desktop\\MBiblliotecaMec\\entrada\\Merdas Mecanica\\Nuno-Engenharia Mecânica\\2ºAno\\1ºSemestre\\TecMec II\\Anos Anteriores\\Nova pasta\\PEÇA 9 MAQUINAÇAO ROLAND.docx",
  "disciplina": "desconhecido",
  "tipo": "teoria",
  "ano": 2,
  "semestre": 1,
  "storage_release_tag": null,
  "storage_url": null,
  "confianca_media": 0.0,
  "assembled_at": "2026-07-03T21:04:18.330922"
}