{
  "id": "82704792352740509089acee121c574ab331307f4b93f5c7bd8e2f03be3dbe8d",
  "title": "Parafusomesa",
  "path_original": "C:\\Users\\anton\\Desktop\\MBiblliotecaMec\\entrada\\Merdas Mecanica\\Francisca- Engenharia Mecânica\\2º ano\\1º Semestre\\Modelação Assistida por Computador\\TL1_FranciscaFabiao\\ParafusoMesa.par",
  "disciplina": "modelacao-assistida-por-computador",
  "tipo": "teoria",
  "ano": 2,
  "semestre": 1,
  "storage_release_tag": null,
  "storage_url": null,
  "confianca_media": 0.0,
  "assembled_at": "2026-07-03T21:03:58.402295"
}