{
  "id": "fa672abdf40329434e63df13823b18b3976aee8830329615f4470da071377b82",
  "title": "Parafuso1",
  "path_original": "C:\\Users\\anton\\Desktop\\MBiblliotecaMec\\entrada\\Merdas Mecanica\\2ºAno\\1ºSemestre\\Modelação Assistida por Computador\\Montagem\\Treino TL2_PL1\\Peças + Montagem\\Parafuso1.par",
  "disciplina": "modelacao-assistida-por-computador",
  "tipo": "teoria",
  "ano": 2,
  "semestre": 1,
  "storage_release_tag": null,
  "storage_url": null,
  "confianca_media": 0.0,
  "assembled_at": "2026-07-03T21:03:45.685153"
}