{
  "id": "904dd517a7f228723296439ddad622984f5690c3be8d3e9b40494ce6997ea0f3",
  "title": "Peca30",
  "path_original": "C:\\Users\\anton\\Desktop\\MBiblliotecaMec\\entrada\\Merdas Mecanica\\Francisca- Engenharia Mecânica\\2º ano\\1º Semestre\\Modelação Assistida por Computador\\TL2_FranciscaFabiao\\SubConjuntosEPecas\\Peças\\Peca30.par",
  "disciplina": "modelacao-assistida-por-computador",
  "tipo": "teoria",
  "ano": 2,
  "semestre": 1,
  "storage_release_tag": null,
  "storage_url": null,
  "confianca_media": 0.0,
  "assembled_at": "2026-07-03T21:03:58.502846"
}