{
  "id": "0b263af684e3a590e0e2fc1a2793b1762c6a8ac0e2dffc8c5122af0b7ae3ce83",
  "title": "Sgt 1",
  "path_original": "C:\\Users\\anton\\Desktop\\MBiblliotecaMec\\entrada\\Merdas Mecanica\\Nuno-Engenharia Mecânica\\3ºAno\\3ºAno\\1ºSemestre\\Automação Industrial\\Teorica 2\\SGT-1.docx",
  "disciplina": "automacao-industrial",
  "tipo": "teoria",
  "ano": 3,
  "semestre": 1,
  "storage_release_tag": null,
  "storage_url": null,
  "confianca_media": 0.0,
  "assembled_at": "2026-07-03T21:04:20.798814"
}