{
  "id": "f3212cd5119838b8a8a43973d79a5cde10f7565d41b1de808fd26ba37fefbdb7",
  "title": "4210688",
  "path_original": "C:\\Users\\anton\\Desktop\\MBiblliotecaMec\\entrada\\Merdas Mecanica\\Nuno-Engenharia Mecânica\\2ºAno\\1ºSemestre\\MAC\\Trabalho Final\\Peças_2\\4210688.par",
  "disciplina": "modelacao-assistida-por-computador",
  "tipo": "trabalhos-projetos",
  "ano": 2,
  "semestre": 1,
  "storage_release_tag": null,
  "storage_url": null,
  "confianca_media": 0.0,
  "assembled_at": "2026-07-03T21:04:16.851954"
}