{
  "id": "bb9d2625221968af3a2d599eaaa9fd7d50acad2cebfbef58373513d4728fb590",
  "title": "Ee_12_13_Eac",
  "path_original": "C:\\Users\\anton\\Desktop\\MBiblliotecaMec\\entrada\\Merdas Mecanica\\2ºAno\\2ºSemestre\\Engenharia Assistida por Computador\\Outros Apontamentos\\Ano 2021-2022\\testesEAC\\EE_12_13_EAC.pdf",
  "disciplina": "engenharia-assistida-por-computador",
  "tipo": "resumos",
  "ano": 2,
  "semestre": 2,
  "storage_release_tag": null,
  "storage_url": null,
  "confianca_media": 0.0,
  "assembled_at": "2026-07-03T21:03:47.063627"
}