{
  "id": "e501263d918d318d3be71562e649305af16ca35bfb5ba7562db4aa227cf51bf4",
  "title": "Escoamento No Interior De Condutas Diagrama Moody",
  "path_original": "C:\\Users\\anton\\Desktop\\MBiblliotecaMec\\entrada\\Merdas Mecanica\\Joel\\Engenharia Mecanica 3º ano\\2º Semestre\\RF\\Aulas Teóricas\\Apontamentos Aula T1-20240325\\Escoamento no interior de condutas Diagrama Moody.pdf",
  "disciplina": "desconhecido",
  "tipo": "teoria",
  "ano": 3,
  "semestre": 2,
  "storage_release_tag": null,
  "storage_url": null,
  "confianca_media": 0.0,
  "assembled_at": "2026-07-03T21:04:14.809325"
}