{
  "id": "fd3feef4f08953a2a6d8400e3ae8e952ddc24832825caef0465031294112823a",
  "title": "Construir_Respostas.Cpython 38",
  "path_original": "C:\\Users\\anton\\Desktop\\MBiblliotecaMec\\entrada\\Merdas Mecanica\\Francisca- Engenharia Mecânica\\1º Ano\\1º Semestre\\Programação\\Projeto\\Mandar para o stor\\__pycache__\\Construir_respostas.cpython-38.pyc",
  "disciplina": "programacao",
  "tipo": "trabalhos-projetos",
  "ano": 1,
  "semestre": 1,
  "storage_release_tag": null,
  "storage_url": null,
  "confianca_media": 0.0,
  "assembled_at": "2026-07-03T21:03:58.203791"
}