{
  "id": "bcc9f2386a23f324a7873bade93c3e2cf0af1bc799c109811e93448455dbc073",
  "title": "Notas_Vf",
  "path_original": "C:\\Users\\anton\\Desktop\\MBiblliotecaMec\\entrada\\Merdas Mecanica\\Nuno-Engenharia Mecânica\\3ºAno\\3ºAno\\2ºSemestre\\GPM\\Docinhos do Toino\\Notas_vf.xlsx",
  "disciplina": "gestao-da-producao-e-manutencao",
  "tipo": "testes-exames",
  "ano": 3,
  "semestre": 2,
  "storage_release_tag": null,
  "storage_url": null,
  "confianca_media": 0.0,
  "assembled_at": "2026-07-03T21:04:23.720849"
}