{
  "id": "449528aa721c657f46fe6c9735b2f0c3a32b332327a5c045dc0392006171e95f",
  "title": "CinemáTica Do Anal Plano",
  "path_original": "C:\\Users\\anton\\Desktop\\MBiblliotecaMec\\entrada\\Merdas Mecanica\\1ºAno\\2ºSemestre\\Mecânica Aplicada\\Aulas TPs\\TP5\\Cinemática do anal plano.pdf",
  "disciplina": "mecanica-aplicada",
  "tipo": "trabalhos-projetos",
  "ano": 1,
  "semestre": 2,
  "storage_release_tag": null,
  "storage_url": null,
  "confianca_media": 0.0,
  "assembled_at": "2026-07-03T21:03:44.629825"
}