{
  "id": "5baa3856d925785d72f5b465cd3498ca7d8f0c34239ca7ddea9adac37e05759c",
  "title": "Reações_Binário",
  "path_original": "C:\\Users\\anton\\Desktop\\MBiblliotecaMec\\entrada\\Merdas Mecanica\\Francisca- Engenharia Mecânica\\1º Ano\\2º Semestre\\Mecânica Aplicada\\Trabalho 2-final\\Reações_Binário.xlsx",
  "disciplina": "mecanica-aplicada",
  "tipo": "trabalhos-projetos",
  "ano": 1,
  "semestre": 2,
  "storage_release_tag": null,
  "storage_url": null,
  "confianca_media": 0.0,
  "assembled_at": "2026-07-03T21:03:58.326283"
}