{
  "id": "f9207341b822e4bb234efaaa38d52f26fe7a146181809c180c7c7083b689931e",
  "title": "Trabalho1_Exercicio6A1",
  "path_original": "C:\\Users\\anton\\Desktop\\MBiblliotecaMec\\entrada\\Merdas Mecanica\\Coisas Daniela Mecapl\\Mecânica Aplicada\\mecanica aplicada\\olalllalal\\trabalho1_exercicio6a1.zcos",
  "disciplina": "mecanica-aplicada",
  "tipo": "trabalhos-projetos",
  "ano": 1,
  "semestre": 2,
  "storage_release_tag": null,
  "storage_url": null,
  "confianca_media": 0.0,
  "assembled_at": "2026-07-03T21:03:57.620841"
}