{
  "id": "d07ae4a74e5e79e12df1d45ecaf8414ac700c4d4f4dc4b81bb2d1afda6cbce2f",
  "title": "Esguicho",
  "path_original": "C:\\Users\\anton\\Desktop\\MBiblliotecaMec\\entrada\\Merdas Mecanica\\Nuno-Engenharia Mecânica\\3ºAno\\3ºAno\\1ºSemestre\\CDP\\Trabalho\\CAD\\Esguicho.SLDPRT",
  "disciplina": "concecao-e-desenvolvimento-de-produto",
  "tipo": "trabalhos-projetos",
  "ano": 3,
  "semestre": 1,
  "storage_release_tag": null,
  "storage_url": null,
  "confianca_media": 0.0,
  "assembled_at": "2026-07-03T21:04:20.965362"
}