{
  "id": "99e7f748a122bf825ea94736c0bfcfc0b846756c993693dd6c6e428507c66a5e",
  "title": "24203916_1640922209286821_1877978224_N",
  "path_original": "C:\\Users\\anton\\Desktop\\MBiblliotecaMec\\entrada\\Merdas Mecanica\\Francisca- Engenharia Mecânica\\3º Ano\\PAF\\PAF\\PAF_Testes_Resumos\\Testes\\24203916_1640922209286821_1877978224_n.jpg",
  "disciplina": "processos-avancados-de-fabrico",
  "tipo": "resumos",
  "ano": 3,
  "semestre": 1,
  "storage_release_tag": null,
  "storage_url": null,
  "confianca_media": 0.0,
  "assembled_at": "2026-07-03T21:04:00.153705"
}