{
  "id": "43d77495386dfdcfc3904f2dc2fe7993637117496d14ce03655f3a9009530c7d",
  "title": "Abs_Cycolacbdt5510_1_Cont",
  "path_original": "C:\\Users\\anton\\Desktop\\MBiblliotecaMec\\entrada\\Merdas Mecanica\\Gonçalo- Engenharia Mecânica\\3ºAno\\1ºSemestre\\Simulação\\TRABALHO 1\\MDXProject20191022\\Report\\Images\\ABS_CYCOLACBDT5510_1\\ABS_CYCOLACBDT5510_1_CONT.bmp",
  "disciplina": "desconhecido",
  "tipo": "trabalhos-projetos",
  "ano": 3,
  "semestre": 1,
  "storage_release_tag": null,
  "storage_url": null,
  "confianca_media": 0.0,
  "assembled_at": "2026-07-03T21:04:02.999205"
}