{
  "id": "6eafa7d9fddcc69ec2b4397542b14ffaf007992ab9db2226354741145d1f79b3",
  "title": "Abs_Cycolacbdt5510_1_Pvt",
  "path_original": "C:\\Users\\anton\\Desktop\\MBiblliotecaMec\\entrada\\Merdas Mecanica\\Gonçalo- Engenharia Mecânica\\3ºAno\\1ºSemestre\\Simulação\\TRABALHO 1\\MDXProject20191022\\Report\\Images\\ABS_CYCOLACBDT5510_1\\ABS_CYCOLACBDT5510_1_PVT.bmp",
  "disciplina": "desconhecido",
  "tipo": "trabalhos-projetos",
  "ano": 3,
  "semestre": 1,
  "storage_release_tag": null,
  "storage_url": null,
  "confianca_media": 0.0,
  "assembled_at": "2026-07-03T21:04:03.007925"
}