{
  "id": "b9f8d0ed1e05d9fb43883eac2302e1d0f306c002eb6017a24fc95dc2e625f3ca",
  "title": "Mdxproject2019121701_001",
  "path_original": "C:\\Users\\anton\\Desktop\\MBiblliotecaMec\\entrada\\Merdas Mecanica\\Gonçalo- Engenharia Mecânica\\3ºAno\\1ºSemestre\\Simulação\\Trabalho_Final\\MDXProject20191217\\Analysis\\Run01\\MDXProject2019121701_001.f2c",
  "disciplina": "desconhecido",
  "tipo": "trabalhos-projetos",
  "ano": 3,
  "semestre": 1,
  "storage_release_tag": null,
  "storage_url": null,
  "confianca_media": 0.0,
  "assembled_at": "2026-07-03T21:04:04.086379"
}