{
  "id": "7c7b7dbb2b0dbc4bbaa0cbc0b83dbd94bc3789e8e271776e232884ad232c22b8",
  "title": "Relatório Tp2",
  "path_original": "C:\\Users\\anton\\Desktop\\MBiblliotecaMec\\entrada\\Merdas Mecanica\\Nuno-Engenharia Mecânica\\3ºAno\\3ºAno\\1ºSemestre\\Anteriores\\Simulação Computacional\\Trabalho Final\\Relatório TP2.docx",
  "disciplina": "desconhecido",
  "tipo": "trabalhos-projetos",
  "ano": 3,
  "semestre": 1,
  "storage_release_tag": null,
  "storage_url": null,
  "confianca_media": 0.0,
  "assembled_at": "2026-07-03T21:04:20.626291"
}