{
  "id": "eeb02626ac4d2c38a8b420828e3930d706aa5c18b93a9789ef7aeef7d4748411",
  "title": "Trabalhofinal.Mfv",
  "path_original": "C:\\Users\\anton\\Desktop\\MBiblliotecaMec\\entrada\\Merdas Mecanica\\Nuno-Engenharia Mecânica\\3ºAno\\3ºAno\\1ºSemestre\\Simulação Computacional\\Trabalho1\\TrabalhoFinal\\MDXProject20181128\\Mesh\\Trabalhofinal.mfv.0",
  "disciplina": "desconhecido",
  "tipo": "trabalhos-projetos",
  "ano": 3,
  "semestre": 1,
  "storage_release_tag": null,
  "storage_url": null,
  "confianca_media": 0.0,
  "assembled_at": "2026-07-03T21:04:23.114387"
}