{
  "id": "80ef335ecf501202b59315713583a880e6de7a0059496cdc1d09d18ed4734e57",
  "title": "Caixa",
  "path_original": "C:\\Users\\anton\\Desktop\\MBiblliotecaMec\\entrada\\Merdas Mecanica\\Nuno-Engenharia Mecânica\\3ºAno\\3ºAno\\2ºSemestre\\Inovação\\Inovação-DiogoPereira_NunoJorge_RicardoBarros_RodrigoAbrunhosa\\CAD\\Caixa.SLDPRT",
  "disciplina": "inovacao-e-empreendedorismo",
  "tipo": "trabalhos-projetos",
  "ano": 3,
  "semestre": 2,
  "storage_release_tag": null,
  "storage_url": null,
  "confianca_media": 0.0,
  "assembled_at": "2026-07-03T21:04:23.856472"
}