{
  "id": "3c52f828590d7f8ca731009f3292f5e3f684bd492e4f5afecb2e43f29d00fbe6",
  "title": "2 Equação De Bernoulli",
  "path_original": "C:\\Users\\anton\\Desktop\\MBiblliotecaMec\\entrada\\Merdas Mecanica\\Joel\\Engenharia Mecanica 2º ano\\1º Semestre\\Termodinâmica\\Aulas teóricas\\Apontamentos Aula T8_T9\\2 Equação de Bernoulli.pdf",
  "disciplina": "termodinamica",
  "tipo": "teoria",
  "ano": 2,
  "semestre": 1,
  "storage_release_tag": null,
  "storage_url": null,
  "confianca_media": 0.0,
  "assembled_at": "2026-07-03T21:04:12.538586"
}