{
  "id": "60d062ba6c2eb8e7174fcc351b7620a2c49f1dc42a0568b7c79b97a261ff44cb",
  "title": "Fe02_Termo_Resol",
  "path_original": "C:\\Users\\anton\\Desktop\\MBiblliotecaMec\\entrada\\Merdas Mecanica\\Joel\\Engenharia Mecanica 2º ano\\1º Semestre\\Termodinâmica\\Aulas teórico-práticas\\Fichas Exercícios - Enunciados\\FE02_Termo_resol.pdf",
  "disciplina": "termodinamica",
  "tipo": "teoria",
  "ano": 2,
  "semestre": 1,
  "storage_release_tag": null,
  "storage_url": null,
  "confianca_media": 0.0,
  "assembled_at": "2026-07-03T21:04:12.573255"
}