{
  "id": "0ff9b387daa740a08183e9fa55eb52314a9fa7018ffc7c416a5415486b9efe82",
  "title": "Aula Teórica 4 14 15 Movimento Geral Plano   Análise Relativa E Absoluta Em Cadeia Aberta",
  "path_original": "C:\\Users\\anton\\Desktop\\MBiblliotecaMec\\entrada\\Merdas Mecanica\\Coisas Daniela Mecapl\\Mecânica Aplicada\\Moodle\\Teorica\\Aula Teórica 4 14 15 Movimento Geral Plano - análise relativa e absoluta em cadeia aberta.pdf",
  "disciplina": "mecanica-aplicada",
  "tipo": "trabalhos-projetos",
  "ano": 1,
  "semestre": 2,
  "storage_release_tag": null,
  "storage_url": null,
  "confianca_media": 0.0,
  "assembled_at": "2026-07-03T21:03:57.761439"
}