{
  "id": "38ea4f6e9c5c1e9c03b08532508aa55afebfa6ef26dc9b03eb8677cb22e0cd82",
  "title": "Tp2_2181117_2181121 Convertido   Cópia",
  "path_original": "C:\\Users\\anton\\Desktop\\MBiblliotecaMec\\entrada\\Merdas Mecanica\\Mecânica Aplicada\\TP2 MecApl\\TP2_2181117_2181121-convertido - Cópia.pptx",
  "disciplina": "mecanica-aplicada",
  "tipo": "trabalhos-projetos",
  "ano": 1,
  "semestre": 2,
  "storage_release_tag": null,
  "storage_url": null,
  "confianca_media": 0.0,
  "assembled_at": "2026-07-03T21:04:15.318438"
}