{
  "id": "7aab9429015c643b6e06055820501bda271cf0ae86c8f57b68186858d41ac4c2",
  "title": "Resolução_1ªpe_22_23",
  "path_original": "C:\\Users\\anton\\Desktop\\MBiblliotecaMec\\entrada\\Merdas Mecanica\\Joel\\Engenharia Mecanica 3º ano\\2º Semestre\\RF\\Frequências e Exames\\1ª Prova Escrita 22_23-20240403\\Resolução_1ªPE_22_23.pdf",
  "disciplina": "desconhecido",
  "tipo": "testes-exames",
  "ano": 3,
  "semestre": 2,
  "storage_release_tag": null,
  "storage_url": null,
  "confianca_media": 0.0,
  "assembled_at": "2026-07-03T21:04:14.920186"
}