{
  "id": "9ededcd327128b1066c54dae75ae4c48e929159916976ea0caf7b1ec6af433d9",
  "title": "Pm2308_Apresentacao_Tipo_Pox",
  "path_original": "C:\\Users\\anton\\Desktop\\MBiblliotecaMec\\entrada\\Merdas Mecanica\\Joel\\Engenharia Mecanica 3º ano\\1º Semestre\\PM\\PM2308_Apresentacao_tipo_POx.pptx",
  "disciplina": "desconhecido",
  "tipo": "teoria",
  "ano": 3,
  "semestre": 1,
  "storage_release_tag": null,
  "storage_url": null,
  "confianca_media": 0.0,
  "assembled_at": "2026-07-03T21:04:14.105574"
}